cia/__init__.py
cia/external.py
cia/investigate.py
cia/report.py
cia/utils.py
cia_python-1.0a8.dist-info/licenses/LICENSE.txt
cia_python-1.0a8.dist-info/METADATA
cia_python-1.0a8.dist-info/WHEEL
cia_python-1.0a8.dist-info/top_level.txt
cia_python-1.0a8.dist-info/RECORD
