Metadata-Version: 2.4
Name: cia_python
Version: 1.0a8
Summary: Cluster Independent Annotation
Home-page: https://github.com/ingmbioinfo/cia
Author: Ivan Ferrari, Mattia Battistella, Francesca Vincenti, Andrea Gobbini, Eugenia Galeota
Author-email: ferrari@ingm.org
License: MIT
Project-URL: Documentation, https://cia-python.readthedocs.io/en/latest/index.html
Project-URL: Source, https://github.com/ingmbioinfo/cia
Platform: any
Classifier: Programming Language :: Python
License-File: LICENSE.txt
Requires-Dist: seaborn
Requires-Dist: numpy
Requires-Dist: pandas
Requires-Dist: AnnData
Requires-Dist: scanpy
Requires-Dist: igraph
Requires-Dist: leidenalg
Requires-Dist: requests
Provides-Extra: testing
Requires-Dist: setuptools; extra == "testing"
Requires-Dist: pytest; extra == "testing"
Requires-Dist: pytest-cov; extra == "testing"
Dynamic: license-file
Dynamic: requires-dist
